screener/__init__.py
screener/__main__.py
screener/checker.py
screener/diagnostic.py
screener/parser/__init__.py
screener/parser/epub.py
screener/parser/kindle.py
screener/reader/__init__.py
screener/reader/abstract.py
screener/reader/epub.py
screener/reader/kindle.py
screener/utils.py
screener-0.5.0.dist-info/METADATA
screener-0.5.0.dist-info/WHEEL
screener-0.5.0.dist-info/entry_points.txt
screener-0.5.0.dist-info/RECORD
