Metadata-Version: 2.1
Name: screener
Version: 0.5.0
Summary: Check e-book files for security and privacy issues.
Home-page: https://github.com/tjkuson/screener/
License: LGPL-3.0-only
Keywords: ebook,security,privacy,epub,mobi,kindle
Author: Tom Kuson
Author-email: mail@tjkuson.me
Requires-Python: >=3.10,<4.0
Classifier: License :: OSI Approved :: GNU Lesser General Public License v3 (LGPLv3)
Classifier: Programming Language :: Python :: 3
Classifier: Programming Language :: Python :: 3.10
Classifier: Programming Language :: Python :: 3.11
Classifier: Topic :: Security
Classifier: Topic :: Utilities
Requires-Dist: EbookLib (>=0.18,<0.19)
Requires-Dist: beautifulsoup4 (>=4.12.2,<5.0.0)
Requires-Dist: mobi (>=0.3.3,<0.4.0)
Project-URL: Repository, https://github.com/tjkuson/screener/
